recharge/__init__.py
recharge/client.py
recharge/exceptions.py
recharge/api/__init__.py
recharge/api/v1/__init__.py
recharge/api/v1/addresses.py
recharge/api/v1/async_batches.py
recharge/api/v1/charges.py
recharge/api/v1/checkouts.py
recharge/api/v1/customers.py
recharge/api/v1/discounts.py
recharge/api/v1/metafields.py
recharge/api/v1/notifications.py
recharge/api/v1/onetimes.py
recharge/api/v1/orders.py
recharge/api/v1/products.py
recharge/api/v1/shop.py
recharge/api/v1/subscriptions.py
recharge/api/v1/tokens.py
recharge/api/v1/webhooks.py
recharge/api/v2/__init__.py
recharge/api/v2/accounts.py
recharge/api/v2/addresses.py
recharge/api/v2/async_batches.py
recharge/api/v2/bundle_selections.py
recharge/api/v2/charges.py
recharge/api/v2/checkouts.py
recharge/api/v2/collections.py
recharge/api/v2/customers.py
recharge/api/v2/discounts.py
recharge/api/v2/events.py
recharge/api/v2/metafields.py
recharge/api/v2/notifications.py
recharge/api/v2/onetimes.py
recharge/api/v2/orders.py
recharge/api/v2/payment_methods.py
recharge/api/v2/plans.py
recharge/api/v2/products.py
recharge/api/v2/retention_strategies.py
recharge/api/v2/store.py
recharge/api/v2/subscriptions.py
recharge/api/v2/tokens.py
recharge/api/v2/webhooks.py
recharge/model/__init__.py
recharge/model/v1/__init__.py
recharge/model/v1/address.py
recharge/model/v1/async_batch.py
recharge/model/v1/charge.py
recharge/model/v1/checkout.py
recharge/model/v1/customer.py
recharge/model/v1/discount.py
recharge/model/v1/metafield.py
recharge/model/v1/notification.py
recharge/model/v1/onetime.py
recharge/model/v1/order.py
recharge/model/v1/product.py
recharge/model/v1/shop.py
recharge/model/v1/subscription.py
recharge/model/v1/token.py
recharge/model/v1/webhook.py
recharge/model/v2/__init__.py
recharge/model/v2/account.py
recharge/model/v2/address.py
recharge/model/v2/async_batch.py
recharge/model/v2/bundle_selection.py
recharge/model/v2/charge.py
recharge/model/v2/checkout.py
recharge/model/v2/collection.py
recharge_api-1.19.5.dist-info/licenses/LICENSE
recharge_api-1.19.5.dist-info/METADATA
recharge_api-1.19.5.dist-info/WHEEL
recharge_api-1.19.5.dist-info/top_level.txt
recharge_api-1.19.5.dist-info/RECORD
